superneuromat/__init__.py
superneuromat/accessor_classes.py
superneuromat/json.py
superneuromat/neuromorphicmodel.py
superneuromat/numba_jit.py
superneuromat/util.py
superneuromat/gpu/cuda.py
superneuromat-3.4.0.dist-info/METADATA
superneuromat-3.4.0.dist-info/WHEEL
superneuromat-3.4.0.dist-info/licenses/LICENSE
superneuromat-3.4.0.dist-info/RECORD
