Metadata-Version: 2.4
Name: superneuromat
Version: 3.4.0
Summary: A fast and scalable matrix-based simulator for Spiking Neural Networks (SNNs).
Project-URL: url, https://github.com/ORNL/superneuromat
Project-URL: Repository, https://github.com/ORNL/superneuromat
Project-URL: Download, https://pypi.org/project/ini2toml/#files
Author: Chathika Gunaratne, Shruti Kulkarni, Robert Patton, Mark Coletti
Author-email: Prasanna Date <datepa@ornl.gov>
Maintainer-email: Prasanna Date <datepa@ornl.gov>
License-Expression: BSD-3-Clause
License-File: LICENSE
Keywords: Fast Neuromorphic Simulator,Matrix-Based Neuromorphic Simulator,Neuromorphic Algorithms,Neuromorphic Computing,Neuromorphic Simulator,Numpy Neuromorphic Simulator
Classifier: Development Status :: 3 - Alpha
Classifier: Programming Language :: Python :: 3
Classifier: Topic :: Scientific/Engineering
Classifier: Topic :: Scientific/Engineering :: Artificial Intelligence
Requires-Python: >=3.9
Requires-Dist: numpy>=1.24.0
Requires-Dist: scipy
Provides-Extra: cuda
Requires-Dist: numba-cuda; extra == 'cuda'
Requires-Dist: numba~=0.61.0; extra == 'cuda'
Requires-Dist: numpy<2.2.0; extra == 'cuda'
Provides-Extra: docs
Requires-Dist: myst-parser; extra == 'docs'
Requires-Dist: numpydoc; extra == 'docs'
Requires-Dist: pydata-sphinx-theme~=0.16.1; extra == 'docs'
Requires-Dist: sphinx; extra == 'docs'
Requires-Dist: sphinx-autodoc-typehints; extra == 'docs'
Requires-Dist: sphinx-copybutton; extra == 'docs'
Requires-Dist: sphinx-design; extra == 'docs'
Requires-Dist: sphinx-togglebutton; extra == 'docs'
Provides-Extra: jit
Requires-Dist: numba; extra == 'jit'
